prettyprompt/__init__.py
prettyprompt/cleaners.py
prettyprompt/converters.py
prettyprompt/sniffers.py
prettyprompt-0.1.5.dist-info/LICENSE
prettyprompt-0.1.5.dist-info/WHEEL
prettyprompt-0.1.5.dist-info/METADATA
prettyprompt-0.1.5.dist-info/RECORD
