Metadata-Version: 2.1
Name: prettyprompt
Version: 0.1.5
Summary: Keeping your prompts clean since 2023
Author-email: Tom Dyson <tom@torchbox.com>
Classifier: License :: OSI Approved :: MIT License
Requires-Dist: beautifulsoup4
Requires-Dist: sqlparse
Requires-Dist: openai
Requires-Dist: spacy
Project-URL: Home, https://github.com/tomdyson/prettyprompt
